{
	"info": {
		"_postman_id": "419759b1-1f52-4637-bf16-5d3f6ae22207",
		"name": "TaskManager Spring Java",
		"schema": "https://schema.getpostman.com/json/collection/v2.0.0/collection.json",
		"_exporter_id": "31999851"
	},
	"item": [
		{
			"name": "Get all Tasks",
			"request": {
				"method": "GET",
				"header": [],
				"url": "http://localhost:3232/tasks"
			},
			"response": []
		},
		{
			"name": "Get task by id",
			"request": {
				"method": "GET",
				"header": [],
				"url": "http://localhost:3232/tasks/1"
			},
			"response": []
		},
		{
			"name": "Create new task",
			"request": {
				"method": "POST",
				"header": [],
				"body": {
					"mode": "raw",
					"raw": "{\n    \"title\": \"Second task\",\n    \"description\" : \"much more details\",\n    \"deadline\" : \"2023-08-02\"\n}",
					"options": {
						"raw": {
							"language": "json"
						}
					}
				},
				"url": "http://localhost:3232/tasks"
			},
			"response": []
		},
		{
			"name": "Update task",
			"request": {
				"method": "PATCH",
				"header": [],
				"body": {
					"mode": "raw",
					"raw": "{\n    \"completed\" : true\n}",
					"options": {
						"raw": {
							"language": "json"
						}
					}
				},
				"url": "http://localhost:3232/tasks/1"
			},
			"response": []
		},
		{
			"name": "Add note to task",
			"request": {
				"method": "POST",
				"header": [],
				"body": {
					"mode": "raw",
					"raw": "{\n    \"title\": \"Second task\",\n    \"description\" : \"much more details\",\n    \"deadline\" : \"2023-08-02\"\n}",
					"options": {
						"raw": {
							"language": "json"
						}
					}
				},
				"url": "http://localhost:3232/tasks"
			},
			"response": []
		},
		{
			"name": "Get all notes of task",
			"request": {
				"method": "GET",
				"header": []
			},
			"response": []
		}
	]
}